<annotation>
	<folder>images</folder>
	<filename>atm_v2_87.jpg</filename>
	<path>D:\Anaconda\ATM Security\image data\v2\images\atm_v2_87.jpg</path>
	<source>
		<database>Unknown</database>
	</source>
	<size>
		<width>1080</width>
		<height>1920</height>
		<depth>3</depth>
	</size>
	<segmented>0</segmented>
	<object>
		<name>person</name>
		<pose>Unspecified</pose>
		<truncated>1</truncated>
		<difficult>0</difficult>
		<bndbox>
			<xmin>482</xmin>
			<ymin>554</ymin>
			<xmax>1080</xmax>
			<ymax>1920</ymax>
		</bndbox>
	</object>
	<object>
		<name>hammer</name>
		<pose>Unspecified</pose>
		<truncated>0</truncated>
		<difficult>0</difficult>
		<bndbox>
			<xmin>422</xmin>
			<ymin>1008</ymin>
			<xmax>648</xmax>
			<ymax>1414</ymax>
		</bndbox>
	</object>
</annotation>
