<annotation>
	<folder>images</folder>
	<filename>Av2_IMG_20220324_120329_0_483pShVe2625.jpg</filename>
	<path>D:\Anaconda\ATM Security\image data\v2\images\Av2_IMG_20220324_120329_0_483pShVe2625.jpg</path>
	<source>
		<database>Unknown</database>
	</source>
	<size>
		<width>636</width>
		<height>828</height>
		<depth>3</depth>
	</size>
	<segmented>0</segmented>
	<object>
		<name>screwdriver</name>
		<pose>Unspecified</pose>
		<truncated>0</truncated>
		<difficult>0</difficult>
		<bndbox>
			<xmin>362</xmin>
			<ymin>267</ymin>
			<xmax>542</xmax>
			<ymax>770</ymax>
		</bndbox>
	</object>
</annotation>
